{
  "name": "Normandy - From Caen to Evreux",
  "theater": "Normandy",
  "authors": "Khopa",
  "recommended_player_faction": "Allies 1944",
  "recommended_enemy_faction": "Germany 1944",
  "description": "<p>This is a light scenario on the Normandy map.</p><p>August 1944, allied forces are pushing from Caen/Carpiquet to the cities of Lisieux and Evreux.<p>Lisieux is an important logistic hub for the Werhmacht, and Evreux airbase is hosting most of the Luftwaffe forces in the region.</p>",
  "miz": "caen_to_evreux.miz",
  "performance": 1,
  "version": "8.1"
}
