{
  "country": "Japan",
  "name": "Japan 1944",
  "authors": "Ghosti",
  "description": "<p>WW2 Japan faction that does not require the WW2 asset pack.</p>",
  "locales": [
    "ja_JP"
  ],
  "aircrafts": [
    "I-16 Ishak",
    "Fw 190 A-8 Anton"
  ],
  "frontline_units": [
    "8.8 cm Flak 18",
    "Panzerkampfwagen IV Ausf. H",
    "Sd.Kfz.251 \"Hanomag\""
  ],
  "artillery_units": [
    "Mortar 2B11 120mm"
  ],
  "logistics_units": [
    "Truck Opel Blitz"
  ],
  "infantry_units": [
    "Infantry AK-74 Rus"
  ],
  "air_defense_units": [
    "8.8 cm Flak 18"
  ],
  "preset_groups": [],
  "naval_units": [],
  "requirements": {},
  "carrier_names": [],
  "helicopter_carrier_names": [],
  "missiles": [],
  "has_jtac": false,
  "doctrine": "ww2",
  "building_set": "ww2free",
  "liveries_overrides": {
    "Fw 190 A-8 Anton": [
      "Fictional IJN 256th Kokutai Rai-153",
      "Fictional IJN Carrier Akagi AI-103",
      "Fictional IJN Carrier Akagi AI-151",
      "Fictional IJN Carrier Soryu BI-112",
      "Fictional IJN OTU Tsukuba Tsu-102"
    ],
    "I-16 Ishak": [
      "Japan"
    ]
  }
}