{
  "country": "Syria",
  "name": "Syria 1973",
  "authors": "Khopa",
  "description": "<p>Syria and Arab armies during the Yom Kippur War</p>",
  "aircrafts": [
    "Mi-8MTV2 Hip",
    "MiG-15bis Fagot",
    "MiG-19P Farmer-B",
    "MiG-21bis Fishbed-N",
    "Su-17M4 Fitter-K"
  ],
  "awacs": [
    "A-50"
  ],
  "tankers": [
    "IL-78M"
  ],
  "frontline_units": [
    "BMP-1",
    "MT-LB",
    "PT-76",
    "S-60 57mm",
    "T-55A",
    "ZSU-57-2 'Sparka'",
    "ZU-23 on Ural-375"
  ],
  "artillery_units": [
    "BM-21 Grad"
  ],
  "logistics_units": [
    "LUV UAZ-469 Jeep",
    "Truck Ural-375"
  ],
  "infantry_units": [
    "Infantry AK-74 Rus",
    "Infantry RPG",
    "Paratrooper AKS"
  ],
  "air_defenses": [
    "EarlyColdWarFlakGenerator",
    "SA2Generator",
    "SA3Generator",
    "SA6Generator",
    "SA8Generator",
    "SA9Generator",
    "ZSU23Generator",
    "ZU23Generator",
    "ZSU57Generator",
    "ZU23UralGenerator"
  ],
  "ewrs": [
    "FlatFaceGenerator"
  ],
  "missiles": [
    "ScudGenerator"
  ],
  "missiles_group_count": 1,
  "aircraft_carrier": [],
  "helicopter_carrier": [],
  "helicopter_carrier_names": [],
  "destroyers": [],
  "cruisers": [],
  "requirements": {},
  "carrier_names": [],
  "navy_generators": [
    "GrishaGroupGenerator"
  ],
  "doctrine": "coldwar"
}